pykarbon/__init__.py
pykarbon/can.py
pykarbon/core.py
pykarbon/hardware.py
pykarbon/i2c.py
pykarbon/pykarbon.py
pykarbon/terminal.py
pykarbon-1.2.0.data/scripts/update_karbon_firmware
pykarbon-1.2.0.dist-info/LICENSE.txt
pykarbon-1.2.0.dist-info/METADATA
pykarbon-1.2.0.dist-info/WHEEL
pykarbon-1.2.0.dist-info/top_level.txt
pykarbon-1.2.0.dist-info/RECORD
