Metadata-Version: 2.1
Name: pykarbon
Version: 1.2.0
Summary: Tools for Karbon hardware interfaces.
Home-page: https://github.com/onlogic/Pykarbon
Author: OnLogic
Author-email: firmwareengineeringteam@onlogic.com
License: BSD-2.0
Platform: UNKNOWN
Classifier: Programming Language :: Python :: 3.5
Classifier: Programming Language :: Python :: 3.6
Classifier: Programming Language :: Python :: 3.7
Classifier: Programming Language :: Python :: 3.8
Classifier: Programming Language :: Python :: 3.9
Classifier: Programming Language :: Python :: 3.10
Classifier: Development Status :: 5 - Production/Stable
Classifier: License :: OSI Approved :: BSD License
Classifier: Operating System :: Microsoft :: Windows
Classifier: Operating System :: POSIX :: Linux
License-File: LICENSE.txt
Requires-Dist: pyserial (>=3.4)
